Metadata-Version: 2.2
Name: access_diction
Version: 1.0.3
Summary: 1
Author: aorphine
Keywords: dict,access_path
Dynamic: author
Dynamic: description
Dynamic: description-content-type
Dynamic: keywords
Dynamic: summary
